.coveragerc
.gitmodules
.travis.yml
AUTHORS.rst
CHANGES.rst
LICENSE.txt
README.rst
docs_requirements.txt
environment.yml
requirements.txt
setup.cfg
setup.py
test-requirements.txt
docs/Makefile
docs/authors.rst
docs/changes.rst
docs/conf.py
docs/img2ts.rst
docs/index.rst
docs/license.rst
docs/reading.rst
docs/varnames.rst
docs/_static/.gitignore
merra/__init__.py
merra/download.py
merra/download_process.py
merra/grid.py
merra/interface.py
merra/reshuffle.py
merra/reshuffling_process.py
merra.egg-info/PKG-INFO
merra.egg-info/SOURCES.txt
merra.egg-info/dependency_links.txt
merra.egg-info/entry_points.txt
merra.egg-info/not-zip-safe
merra.egg-info/requires.txt
merra.egg-info/top_level.txt
tests/__init__.py
tests/merra-test-data
tests/test_download.py
tests/test_grid.py
tests/test_interface.py
tests/test_reshuffle.py
tests/folder_test/failure/dummy_folder_1/.test
tests/folder_test/failure/dummy_folder_2/.test
tests/folder_test/success/2017/.test
tests/folder_test/success/2017/01/.test
tests/folder_test/success/2018/.test
tests/folder_test/success/2018/11/.test
tests/folder_test/success/2018/12/.test
tests/folder_test/success/dummy_folder/.test