Metadata-Version: 2.1
Name: merra
Version: 0.1
Summary: Readers and converters for data from the MERRA2 reanalysis Model.
Home-page: https://github.com/TUW-GEO/merra
Author: Felix Zaussinger
Author-email: felix.zaussinger@geo.tuwien.ac.at
License: none
Platform: UNKNOWN
Classifier: Development Status :: 4 - Beta
Classifier: Programming Language :: Python
Provides-Extra: test
